gpg_sop_wrapper/__init__.py
gpg_sop_wrapper/__main__.py
gpg_sop_wrapper/defs.py
gpg_sop_wrapper/py.typed
gpg_sop_wrapper-0.1.0.dist-info/METADATA
gpg_sop_wrapper-0.1.0.dist-info/WHEEL
gpg_sop_wrapper-0.1.0.dist-info/entry_points.txt
gpg_sop_wrapper-0.1.0.dist-info/RECORD
