Metadata-Version: 2.3
Name: gpg-sop-wrapper
Version: 0.1.0
Summary: Wrap a SOP tool, e.g. sqop, and simulate a GnuPG interface
Project-URL: Homepage, https://devel.ringlet.net/misc/gpg-sop-wrapper/
Project-URL: Changes, https://devel.ringlet.net/misc/gpg-sop-wrapper/changes/
Project-URL: Issue Tracker, https://gitlab.com/ppentchev/gpg-sop-wrapper/-/issues
Project-URL: Source Code, https://gitlab.com/ppentchev/gpg-sop-wrapper
Author-email: Peter Pentchev <roam@ringlet.net>
License: BSD-2-Clause
Classifier: Development Status :: 3 - Alpha
Classifier: Environment :: Console
Classifier: Intended Audience :: Developers
Classifier: License :: DFSG approved
Classifier: License :: Freely Distributable
Classifier: License :: OSI Approved :: BSD License
Classifier: Operating System :: OS Independent
Classifier: Programming Language :: Python
Classifier: Programming Language :: Python :: 3
Classifier: Programming Language :: Python :: 3 :: Only
Classifier: Programming Language :: Python :: 3.11
Classifier: Programming Language :: Python :: 3.12
Classifier: Programming Language :: Python :: 3.13
Classifier: Topic :: Security :: Cryptography
Classifier: Topic :: Utilities
Classifier: Typing :: Typed
Requires-Python: >=3.11
Requires-Dist: click<9,>=8
